<?xml version="1.0" encoding="utf-8"?>
<data migrato="1.0.1">
	<xml_id>measure_112</xml_id>
	<field>
		<name>CODE</name>
		<value>112</value>
	</field>
	<field>
		<name>MEASURE_TITLE</name>
		<value>Литр</value>
	</field>
	<field>
		<name>SYMBOL_RUS</name>
		<value>л.</value>
	</field>
	<field>
		<name>SYMBOL_INTL</name>
		<value>l</value>
	</field>
	<field>
		<name>SYMBOL_LETTER_INTL</name>
		<value>LTR</value>
	</field>
	<field>
		<name>IS_DEFAULT</name>
		<value>N</value>
	</field>
	<field>
		<name>SYMBOL</name>
		<value>л.</value>
	</field>
</data>